Auth.py
calc_hash.py
change_log_state.py
get_snapshots.py
main.py
subsys-0.2.9.dist-info/METADATA
subsys-0.2.9.dist-info/WHEEL
subsys-0.2.9.dist-info/entry_points.txt
subsys-0.2.9.dist-info/top_level.txt
subsys-0.2.9.dist-info/RECORD
