Metadata-Version: 2.1
Name: subsys
Version: 0.2.9
Summary: cli for assignment submission
Home-page: UNKNOWN
Author: Patrick Mushimiye
Author-email: patrick.mushimiye@amalitech.org
License: UNKNOWN
Platform: UNKNOWN
Requires-Dist: Click
